conclave/__init__.py
conclave/conclave_client.py
conclave-1.0.0.dist-info/LICENCE.md
conclave-1.0.0.dist-info/METADATA
conclave-1.0.0.dist-info/WHEEL
conclave-1.0.0.dist-info/top_level.txt
conclave-1.0.0.dist-info/RECORD
