Metadata-Version: 2.1
Name: conclave
Version: 1.0.0
Summary: Official Conclave Python Client
Home-page: https://github.com/conclave-network/conclave-python-client
Author: Noel O'Donnell
Author-email: UNKNOWN
License: GPL3
Keywords: bitcoin,conclave
Platform: UNKNOWN
